{
	"info": {
		"_postman_id": "03377774-c076-470c-a303-c7ba579befd4",
		"name": "TestWork",
		"schema": "https://schema.getpostman.com/json/collection/v2.1.0/collection.json"
	},
	"item": [
		{
			"name": "getAllGenres",
			"request": {
				"method": "GET",
				"header": [],
				"url": null
			},
			"response": []
		},
		{
			"name": "getAllGenresWithMovies",
			"request": {
				"method": "GET",
				"header": [],
				"url": null
			},
			"response": []
		},
		{
			"name": "getGenresSortedAsc",
			"request": {
				"method": "GET",
				"header": [],
				"url": null
			},
			"response": []
		},
		{
			"name": "GetGenresSortedDesc",
			"request": {
				"method": "GET",
				"header": [],
				"url": null
			},
			"response": []
		},
		{
			"name": "getAllMovies",
			"request": {
				"method": "GET",
				"header": [],
				"url": null
			},
			"response": []
		},
		{
			"name": "getAllMoviesSortedAsc",
			"request": {
				"method": "GET",
				"header": [],
				"url": null
			},
			"response": []
		},
		{
			"name": "getAllMoviesSortedDesc",
			"request": {
				"method": "GET",
				"header": [],
				"url": null
			},
			"response": []
		},
		{
			"name": "movieSearch",
			"request": {
				"method": "GET",
				"header": [],
				"url": null
			},
			"response": []
		},
		{
			"name": "genreSearch",
			"request": {
				"method": "GET",
				"header": [],
				"url": null
			},
			"response": []
		},
		{
			"name": "getGenreById",
			"request": {
				"method": "GET",
				"header": [],
				"url": null
			},
			"response": []
		},
		{
			"name": "getMovieById",
			"request": {
				"method": "GET",
				"header": [],
				"url": null
			},
			"response": []
		}
	]
}